rungutan/__init__.py
rungutan/authentication.py
rungutan/config.py
rungutan/configure.py
rungutan/crons.py
rungutan/csv.py
rungutan/file.py
rungutan/notifications.py
rungutan/print_format.py
rungutan/raw_results.py
rungutan/results.py
rungutan/send_request.py
rungutan/team.py
rungutan/templates.py
rungutan/tests.py
rungutan/vault.py
rungutan-1.10.0.dist-info/LICENSE.txt
rungutan-1.10.0.dist-info/METADATA
rungutan-1.10.0.dist-info/WHEEL
rungutan-1.10.0.dist-info/entry_points.txt
rungutan-1.10.0.dist-info/top_level.txt
rungutan-1.10.0.dist-info/RECORD
