Metadata-Version: 2.1
Name: rungutan
Version: 1.10.0
Summary: CLI for Rungutan - the first API Load Testing SaaS platform worldwide, 100% Serverless, which  helps you simulate workflows to emulate user experience, so it's easier to design workflow oriented strategies.
Home-page: https://github.com/Rungutan/rungutan-cli
Download-URL: https://github.com/Rungutan/rungutan-cli/archive/1.10.0.tar.gz
Author: Rungutan
Author-email: support@rungutan.com
Project-URL: Bug Reports, https://github.com/Rungutan/rungutan-cli/issues
Project-URL: Source, https://github.com/Rungutan/rungutan-cli/
Keywords: rungutan rungutan-cli rungutan_cli cli load testing load-testing load_testing stressstress-testing stress_testing api api-testing api_testing api_load_testing api-load-testingapi_stress_testing api-stress-testing performance performance-testing performance_testingapi-performance-testing api_performance_testing serverless workflow-testing workflow_testing
Classifier: Development Status :: 5 - Production/Stable
Classifier: Intended Audience :: Developers
Classifier: Intended Audience :: Information Technology
Classifier: Intended Audience :: System Administrators
Classifier: Topic :: Software Development :: Testing
Classifier: Topic :: Software Development :: Quality Assurance
Classifier: Topic :: Software Development :: Testing :: Acceptance
Classifier: Topic :: Software Development :: Testing :: BDD
Classifier: Topic :: Software Development :: Testing :: Mocking
Classifier: Topic :: Software Development :: Testing :: Traffic Generation
Classifier: Topic :: Software Development :: Testing :: Unit
Classifier: License :: OSI Approved :: MIT License
Classifier: Programming Language :: Python :: 3.5
Classifier: Programming Language :: Python :: 3.6
Classifier: Programming Language :: Python :: 3.7
Classifier: Programming Language :: Python :: 3.8
Classifier: Programming Language :: Python :: 3.9
Classifier: Programming Language :: Python :: 3.10
Classifier: Programming Language :: Python :: 3.11
Classifier: Programming Language :: Python :: 3.12
Requires-Python: >=3.5, <4
License-File: LICENSE.txt
Requires-Dist: simplejson
Provides-Extra: test
Requires-Dist: coverage ; extra == 'test'
